INA3221_linux/__init__.py
ina3221_linux-0.1.0.dist-info/licenses/LICENSE
ina3221_linux-0.1.0.dist-info/METADATA
ina3221_linux-0.1.0.dist-info/WHEEL
ina3221_linux-0.1.0.dist-info/top_level.txt
ina3221_linux-0.1.0.dist-info/RECORD
