Metadata-Version: 2.4
Name: INA3221-linux
Version: 0.1.0
Summary: INA3221 shunt and bus voltage monitor library for linux
Author-email: Chandra Wijaya Sentosa <chandra.w.sentosa@gmail.com>
License-Expression: MIT
Project-URL: Homepage, https://github.com/chandrawi/INA3221_linux
Project-URL: Issues, https://github.com/chandrawi/INA3221_linux/issues
Classifier: Programming Language :: Python :: 3
Classifier: Operating System :: OS Independent
Requires-Python: >=3.7
License-File: LICENSE
Requires-Dist: smbus2
Dynamic: license-file
